django_payments_blockbee-1.0.5.dist-info/licenses/LICENSE
payments_blockbee/__init__.py
django_payments_blockbee-1.0.5.dist-info/METADATA
django_payments_blockbee-1.0.5.dist-info/WHEEL
django_payments_blockbee-1.0.5.dist-info/top_level.txt
django_payments_blockbee-1.0.5.dist-info/RECORD
