Metadata-Version: 2.4
Name: django-payments-blockbee
Version: 1.0.5
Summary: BlockBee Checkout backend for django-payments.
Home-page: https://github.com/blockbee-io/django-payments-blockbee
Author: BlockBee
Author-email: support@blockbee.io
License: MIT
Project-URL: Homepage, https://github.com/blockbee-io/django-payments-blockbee
Project-URL: Source, https://github.com/blockbee-io/django-payments-blockbee
Project-URL: Tracker, https://github.com/blockbee-io/django-payments-blockbee/issues
Keywords: django,payments,django-payments,blockbee,crypto,checkout
Classifier: Development Status :: 5 - Production/Stable
Classifier: Intended Audience :: Developers
Classifier: License :: OSI Approved :: MIT License
Classifier: Framework :: Django
Classifier: Framework :: Django :: 3.2
Classifier: Framework :: Django :: 4.2
Classifier: Framework :: Django :: 5.0
Classifier: Programming Language :: Python
Classifier: Programming Language :: Python :: 3
Classifier: Programming Language :: Python :: 3 :: Only
Classifier: Programming Language :: Python :: 3.8
Classifier: Programming Language :: Python :: 3.9
Classifier: Programming Language :: Python :: 3.10
Classifier: Programming Language :: Python :: 3.11
Classifier: Programming Language :: Python :: 3.12
Classifier: Programming Language :: Python :: 3.13
Classifier: Topic :: Internet :: WWW/HTTP
Classifier: Topic :: Software Development :: Libraries :: Python Modules
Requires-Python: >=3.8
License-File: LICENSE
Requires-Dist: django>=3.2
Requires-Dist: django-payments>=2.0
Requires-Dist: requests>=2.25
Requires-Dist: python-blockbee>=2.1.1
Requires-Dist: cryptography>=45.0.0
Dynamic: author
Dynamic: author-email
Dynamic: classifier
Dynamic: description
Dynamic: description-content-type
Dynamic: home-page
Dynamic: keywords
Dynamic: license
Dynamic: license-file
Dynamic: project-url
Dynamic: requires-dist
Dynamic: requires-python
Dynamic: summary
